framdata/__init__.py
framdata/database_names/DatabaseNames.py
framdata/database_names/DemandNames.py
framdata/database_names/H5Names.py
framdata/database_names/HydroBypassNames.py
framdata/database_names/HydroGeneratorNames.py
framdata/database_names/HydroInflowNames.py
framdata/database_names/HydroModulesNames.py
framdata/database_names/HydroPumpNames.py
framdata/database_names/HydroReservoirNames.py
framdata/database_names/ThermalNames.py
framdata/database_names/TimeVectorMetadataNames.py
framdata/database_names/TransmissionNames.py
framdata/database_names/WindSolarNames.py
framdata/database_names/YamlNames.py
framdata/database_names/__init__.py
framdata/database_names/_attribute_metadata_names.py
framdata/database_names/_base_names.py
framdata/database_names/nodes_names.py
framdata/database_names/validation_functions.py
framdata/file_editors/NVEFileEditor.py
framdata/file_editors/NVEH5TimeVectorEditor.py
framdata/file_editors/NVEParquetTimeVectorEditor.py
framdata/file_editors/__init__.py
framdata/loaders/NVETimeVectorLoader.py
framdata/loaders/__init__.py
framdata/loaders/curve_loaders.py
framdata/loaders/time_vector_loaders.py
framdata/populators/NVEEnergyModelPopulator.py
framdata/populators/NVEPathManager.py
framdata/populators/_DataObjectManager.py
framdata/populators/_DatabaseInterpreter.py
framdata/populators/timevector_populators.py
fram_data-0.1.1.dist-info/METADATA
fram_data-0.1.1.dist-info/WHEEL
fram_data-0.1.1.dist-info/licenses/LICENSE.md
fram_data-0.1.1.dist-info/RECORD
